sc_utilities/__init__.py
sc_utilities/config_utils.py
sc_utilities/excel_utils.py
sc_utilities/exceptions.py
sc_utilities/file_utils.py
sc_utilities/log_utils.py
sc_utilities/singleton.py
tests/__init__.py
tests/excel_utils_tests.py
tests/test_config.py
tests/singleton/__init__.py
tests/singleton/singleton_test.py
sc_utilities-0.0.17.dist-info/LICENSE
sc_utilities-0.0.17.dist-info/METADATA
sc_utilities-0.0.17.dist-info/WHEEL
sc_utilities-0.0.17.dist-info/top_level.txt
sc_utilities-0.0.17.dist-info/RECORD
