Metadata-Version: 2.1
Name: sc-utilities
Version: 0.0.17
Summary: Some Python Utilities, Such as file, logging and singleton
Home-page: https://github.com/Scott-Lau/sc-utilities
Author: Scott Lau
Author-email: exceedego@126.com
License: MIT
Keywords: Python Utilities Singleton
Platform: POSIX
Classifier: Programming Language :: Python :: 3
Classifier: Programming Language :: Python :: 3.8
Classifier: Programming Language :: Python :: 3.9
Classifier: Programming Language :: Python :: 3.10
Classifier: Programming Language :: Python :: 3.11
Classifier: Operating System :: OS Independent
Classifier: Topic :: Software Development
Classifier: Topic :: Utilities
Requires-Python: >=3.8
License-File: LICENSE
Requires-Dist: PyYAML ==6.0.2
